README.rst
setup.cfg
setup.py
s4cmb/__init__.py
s4cmb/celestial_body_trajectories.py
s4cmb/config_s4cmb.py
s4cmb/detector_pointing.py
s4cmb/detector_pointing_f.f90
s4cmb/input_sky.py
s4cmb/instrument.py
s4cmb/scanning_strategy.py
s4cmb/scanning_strategy_f.f90
s4cmb/systematics.py
s4cmb/systematics_f.f90
s4cmb/tod.py
s4cmb/tod_f.f90
s4cmb/tools.py
s4cmb/xpure.py
s4cmb.egg-info/PKG-INFO
s4cmb.egg-info/SOURCES.txt
s4cmb.egg-info/dependency_links.txt
s4cmb.egg-info/requires.txt
s4cmb.egg-info/top_level.txt